call_center/__init__.py
call_center/_agent.py
call_center/_compat.py
call_center/_version.py
call_center-0.1.0.dist-info/LICENSE
call_center-0.1.0.dist-info/METADATA
call_center-0.1.0.dist-info/WHEEL
call_center-0.1.0.dist-info/top_level.txt
call_center-0.1.0.dist-info/RECORD
