Metadata-Version: 2.1
Name: call-center
Version: 0.1.0
Summary: OpenAI function calling utility
Author-email: Philip Meier <github.pmeier@posteo.de>
License: BSD 3-Clause License
Project-URL: Repository, https://github.com/pmeier/call-center
Classifier: Development Status :: 4 - Beta
Classifier: Programming Language :: Python :: 3.9
Classifier: Programming Language :: Python :: 3.10
Classifier: Programming Language :: Python :: 3.11
Classifier: Programming Language :: Python :: 3.12
Requires-Python: >=3.9
License-File: LICENSE
Requires-Dist: docstring-parser
Requires-Dist: httpx
Requires-Dist: httpx-sse
Requires-Dist: pydantic >=2
